{"DATA_SOURCE":"OS_WD_PERSONS","RECORD_ID":"Q101452678","RECORD_TYPE":null,"LAST_CHANGE":"2024-03-10T15:36:30","NAMES":[{"NAME_TYPE":"PRIMARY","NAME_FULL":"Ambassador of Saudi Arabia to Pakistan"}],"COUNTRIES":[{"CITIZENSHIP":"sa"}],"IDENTIFIERS":[{"OTHER_ID_TYPE":"wikidataId","OTHER_ID_NUMBER":"Q101452678"},{"TRUSTED_ID_TYPE":"WIKIDATA","TRUSTED_ID_NUMBER":"Q101452678"}],"URL":"https://opensanctions.org/entities/Q101452678/"}
{"DATA_SOURCE":"OS_WD_PERSONS","RECORD_ID":"Q102311321","RECORD_TYPE":null,"LAST_CHANGE":"2024-03-10T15:36:30","NAMES":[{"NAME_TYPE":"PRIMARY","NAME_FULL":"Saudi Arabia ambassador to Turkmenistan"}],"COUNTRIES":[{"CITIZENSHIP":"sa"}],"IDENTIFIERS":[{"OTHER_ID_TYPE":"wikidataId","OTHER_ID_NUMBER":"Q102311321"},{"TRUSTED_ID_TYPE":"WIKIDATA","TRUSTED_ID_NUMBER":"Q102311321"}],"URL":"https://opensanctions.org/entities/Q102311321/"}
{"DATA_SOURCE":"OS_WD_PERSONS","RECORD_ID":"Q10279737","RECORD_TYPE":"PERSON","LAST_CHANGE":"2024-03-10T15:36:30","NAMES":[{"NAME_TYPE":"PRIMARY","NAME_FULL":"Fahd Hariri"}],"GENDER":"M","DATES":[{"DATE_OF_BIRTH":"1982-01-01"}],"ADDRESSES":[{"PLACE_OF_BIRTH":"Saudi Arabia"}],"COUNTRIES":[{"NATIONALITY":"lb"},{"NATIONALITY":"sa"}],"RELATIONSHIPS":[{"REL_ANCHOR_DOMAIN":"OPEN_SANCTIONS","REL_ANCHOR_KEY":"Q296771","REL_POINTER_ROLE":"Family","REL_POINTER_DOMAIN":"OPEN_SANCTIONS","REL_POINTER_KEY":"Q10279737"}],"IDENTIFIERS":[{"OTHER_ID_TYPE":"wikidataId","OTHER_ID_NUMBER":"Q10279737"},{"TRUSTED_ID_TYPE":"WIKIDATA","TRUSTED_ID_NUMBER":"Q10279737"}],"URL":"https://opensanctions.org/entities/Q10279737/"}
{"DATA_SOURCE":"OS_WD_PERSONS","RECORD_ID":"Q14915225","RECORD_TYPE":null,"LAST_CHANGE":"2024-03-10T15:36:30","NAMES":[{"NAME_TYPE":"PRIMARY","NAME_FULL":"Prime Minister of Lebanon"}],"COUNTRIES":[{"CITIZENSHIP":"lb"}],"IDENTIFIERS":[{"OTHER_ID_TYPE":"wikidataId","OTHER_ID_NUMBER":"Q14915225"},{"TRUSTED_ID_TYPE":"WIKIDATA","TRUSTED_ID_NUMBER":"Q14915225"}],"URL":"https://opensanctions.org/entities/Q14915225/"}
{"DATA_SOURCE":"OS_WD_PERSONS","RECORD_ID":"Q192778","RECORD_TYPE":"PERSON","LAST_CHANGE":"2024-03-10T15:36:30","NAMES":[{"NAME_TYPE":"PRIMARY","NAME_FULL":"Hariri"},{"NAME_TYPE":"ALIAS","NAME_FULL":"Rafik"},{"NAME_TYPE":"ALIAS","NAME_FULL":"Rafic Hariri"}],"GENDER":"M","DATES":[{"DATE_OF_BIRTH":"1944-11-01"}],"ADDRESSES":[{"PLACE_OF_BIRTH":"Sidon"}],"COUNTRIES":[{"NATIONALITY":"lb"},{"NATIONALITY":"sa"}],"RELATIONSHIPS":[{"REL_ANCHOR_DOMAIN":"OPEN_SANCTIONS","REL_ANCHOR_KEY":"Q296771","REL_POINTER_ROLE":"Family","REL_POINTER_DOMAIN":"OPEN_SANCTIONS","REL_POINTER_KEY":"Q192778"}],"IDENTIFIERS":[{"OTHER_ID_TYPE":"wikidataId","OTHER_ID_NUMBER":"Q192778"},{"TRUSTED_ID_TYPE":"WIKIDATA","TRUSTED_ID_NUMBER":"Q192778"}],"URL":"https://opensanctions.org/entities/Q192778/"}
{"DATA_SOURCE":"OS_WD_PERSONS","RECORD_ID":"Q20424718","RECORD_TYPE":"PERSON","LAST_CHANGE":"2024-03-10T15:36:30","NAMES":[{"NAME_TYPE":"PRIMARY","NAME_FULL":"Nidal Boustany"}],"GENDER":"F","DATES":[{"DATE_OF_BIRTH":"2000-01-01"}],"RELATIONSHIPS":[{"REL_ANCHOR_DOMAIN":"OPEN_SANCTIONS","REL_ANCHOR_KEY":"Q296771","REL_POINTER_ROLE":"Family","REL_POINTER_DOMAIN":"OPEN_SANCTIONS","REL_POINTER_KEY":"Q20424718"}],"IDENTIFIERS":[{"OTHER_ID_TYPE":"wikidataId","OTHER_ID_NUMBER":"Q20424718"},{"TRUSTED_ID_TYPE":"WIKIDATA","TRUSTED_ID_NUMBER":"Q20424718"}],"URL":"https://opensanctions.org/entities/Q20424718/"}
{"DATA_SOURCE":"OS_WD_PERSONS","RECORD_ID":"Q21328581","RECORD_TYPE":null,"LAST_CHANGE":"2024-03-10T15:36:30","NAMES":[{"NAME_TYPE":"PRIMARY","NAME_FULL":"Member of the Parliament of Lebanon"}],"COUNTRIES":[{"CITIZENSHIP":"lb"}],"IDENTIFIERS":[{"OTHER_ID_TYPE":"wikidataId","OTHER_ID_NUMBER":"Q21328581"},{"TRUSTED_ID_TYPE":"WIKIDATA","TRUSTED_ID_NUMBER":"Q21328581"}],"URL":"https://opensanctions.org/entities/Q21328581/"}
{"DATA_SOURCE":"OS_WD_PERSONS","RECORD_ID":"Q296771","RECORD_TYPE":"PERSON","LAST_CHANGE":"2024-03-10T15:36:30","NAMES":[{"NAME_TYPE":"PRIMARY","NAME_FULL":"Saad Hariri"},{"NAME_TYPE":"ALIAS","NAME_FULL":"Hariri"},{"NAME_TYPE":"ALIAS","NAME_FULL":"Sa'd al-Din"}],"GENDER":"M","DATES":[{"DATE_OF_BIRTH":"1970-04-18"}],"ADDRESSES":[{"PLACE_OF_BIRTH":"Riyadh"}],"COUNTRIES":[{"NATIONALITY":"lb"},{"NATIONALITY":"fr"},{"NATIONALITY":"sa"}],"CONTACTS":[{"WEBSITE_ADDRESS":"http://www.saadhariri.com/"}],"RELATIONSHIPS":[{"REL_ANCHOR_DOMAIN":"OPEN_SANCTIONS","REL_ANCHOR_KEY":"Q296771","REL_POINTER_ROLE":"Family","REL_POINTER_DOMAIN":"OPEN_SANCTIONS","REL_POINTER_KEY":"Q20424718"},{"REL_ANCHOR_DOMAIN":"OPEN_SANCTIONS","REL_ANCHOR_KEY":"Q296771","REL_POINTER_ROLE":"Family","REL_POINTER_DOMAIN":"OPEN_SANCTIONS","REL_POINTER_KEY":"Q800179"},{"REL_ANCHOR_DOMAIN":"OPEN_SANCTIONS","REL_ANCHOR_KEY":"Q296771","REL_POINTER_ROLE":"Family","REL_POINTER_DOMAIN":"OPEN_SANCTIONS","REL_POINTER_KEY":"Q10279737"},{"REL_ANCHOR_DOMAIN":"OPEN_SANCTIONS","REL_ANCHOR_KEY":"Q296771","REL_POINTER_ROLE":"Family","REL_POINTER_DOMAIN":"OPEN_SANCTIONS","REL_POINTER_KEY":"Q192778"}],"IDENTIFIERS":[{"OTHER_ID_TYPE":"wikidataId","OTHER_ID_NUMBER":"Q296771"},{"TRUSTED_ID_TYPE":"WIKIDATA","TRUSTED_ID_NUMBER":"Q296771"}],"URL":"https://opensanctions.org/entities/Q296771/"}
{"DATA_SOURCE":"OS_WD_PERSONS","RECORD_ID":"Q307152","RECORD_TYPE":"PERSON","LAST_CHANGE":"2024-03-10T15:36:30","NAMES":[{"NAME_TYPE":"PRIMARY","NAME_FULL":"Abd al-Aziz"},{"NAME_TYPE":"ALIAS","NAME_FULL":"Abd al-Aziz al-Ghadir"}],"GENDER":"M","DATES":[{"DATE_OF_BIRTH":"1960-01-01"}],"ADDRESSES":[{"PLACE_OF_BIRTH":"Riyadh"}],"COUNTRIES":[{"NATIONALITY":"sa"}],"IDENTIFIERS":[{"OTHER_ID_TYPE":"wikidataId","OTHER_ID_NUMBER":"Q307152"},{"TRUSTED_ID_TYPE":"WIKIDATA","TRUSTED_ID_NUMBER":"Q307152"}],"URL":"https://opensanctions.org/entities/Q307152/"}
{"DATA_SOURCE":"OS_WD_PERSONS","RECORD_ID":"Q307185","RECORD_TYPE":"PERSON","LAST_CHANGE":"2024-03-10T15:36:30","NAMES":[{"NAME_TYPE":"PRIMARY","NAME_FULL":"Abd al-Aziz"},{"NAME_TYPE":"ALIAS","NAME_FULL":"Sheikh Abdulaziz al-Sheikh"}],"GENDER":"M","DATES":[{"DATE_OF_BIRTH":"1943-02-10"}],"ADDRESSES":[{"PLACE_OF_BIRTH":"Riyadh"}],"COUNTRIES":[{"NATIONALITY":"sa"}],"IDENTIFIERS":[{"OTHER_ID_TYPE":"wikidataId","OTHER_ID_NUMBER":"Q307185"},{"TRUSTED_ID_TYPE":"WIKIDATA","TRUSTED_ID_NUMBER":"Q307185"}],"URL":"https://opensanctions.org/entities/Q307185/"}
{"DATA_SOURCE":"OS_WD_PERSONS","RECORD_ID":"Q317948","RECORD_TYPE":"PERSON","LAST_CHANGE":"2024-03-10T15:36:30","NAMES":[{"NAME_TYPE":"PRIMARY","NAME_FULL":"Abd al-Rahman"},{"NAME_TYPE":"ALIAS","NAME_FULL":"Abdul Rahman Al-Sudais"}],"GENDER":"M","DATES":[{"DATE_OF_BIRTH":"1962-11-22"}],"ADDRESSES":[{"PLACE_OF_BIRTH":"Al Bukayriyah"}],"COUNTRIES":[{"NATIONALITY":"sa"}],"IDENTIFIERS":[{"OTHER_ID_TYPE":"wikidataId","OTHER_ID_NUMBER":"Q317948"},{"TRUSTED_ID_TYPE":"WIKIDATA","TRUSTED_ID_NUMBER":"Q317948"}],"URL":"https://opensanctions.org/entities/Q317948/"}
{"DATA_SOURCE":"OS_WD_PERSONS","RECORD_ID":"Q5594817","RECORD_TYPE":null,"LAST_CHANGE":"2024-03-10T15:36:30","NAMES":[{"NAME_TYPE":"PRIMARY","NAME_FULL":"Grand Mufti of Saudi Arabia"}],"COUNTRIES":[{"CITIZENSHIP":"sa"}],"IDENTIFIERS":[{"OTHER_ID_TYPE":"wikidataId","OTHER_ID_NUMBER":"Q5594817"},{"TRUSTED_ID_TYPE":"WIKIDATA","TRUSTED_ID_NUMBER":"Q5594817"}],"URL":"https://opensanctions.org/entities/Q5594817/"}
{"DATA_SOURCE":"OS_WD_PERSONS","RECORD_ID":"Q61589","RECORD_TYPE":"PERSON","LAST_CHANGE":"2024-03-10T15:36:30","NAMES":[{"NAME_TYPE":"PRIMARY","NAME_FULL":"Saleh Al-Fawzan"},{"NAME_TYPE":"ALIAS","NAME_FULL":"Salih"}],"GENDER":"M","DATES":[{"DATE_OF_BIRTH":"1933-09-28"}],"ADDRESSES":[{"PLACE_OF_BIRTH":"Al Shimasiyah"}],"COUNTRIES":[{"NATIONALITY":"sa"}],"CONTACTS":[{"WEBSITE_ADDRESS":"http://www.alfawzan.af.org.sa/"}],"IDENTIFIERS":[{"OTHER_ID_TYPE":"wikidataId","OTHER_ID_NUMBER":"Q61589"},{"TRUSTED_ID_TYPE":"WIKIDATA","TRUSTED_ID_NUMBER":"Q61589"}],"URL":"https://opensanctions.org/entities/Q61589/"}
{"DATA_SOURCE":"OS_WD_PERSONS","RECORD_ID":"Q800179","RECORD_TYPE":"PERSON","LAST_CHANGE":"2024-03-10T15:36:30","NAMES":[{"NAME_TYPE":"PRIMARY","NAME_FULL":"Bahaa Hariri"},{"NAME_TYPE":"ALIAS","NAME_FULL":"Hariri"}],"GENDER":"M","DATES":[{"DATE_OF_BIRTH":"1966-01-01"}],"ADDRESSES":[{"PLACE_OF_BIRTH":"Lebanon"}],"COUNTRIES":[{"NATIONALITY":"lb"}],"RELATIONSHIPS":[{"REL_ANCHOR_DOMAIN":"OPEN_SANCTIONS","REL_ANCHOR_KEY":"Q296771","REL_POINTER_ROLE":"Family","REL_POINTER_DOMAIN":"OPEN_SANCTIONS","REL_POINTER_KEY":"Q800179"}],"IDENTIFIERS":[{"OTHER_ID_TYPE":"wikidataId","OTHER_ID_NUMBER":"Q800179"},{"TRUSTED_ID_TYPE":"WIKIDATA","TRUSTED_ID_NUMBER":"Q800179"}],"URL":"https://opensanctions.org/entities/Q800179/"}
